{
  "generated_at": "2026-05-13T03:44:24.097436",
  "universe": "nifty500",
  "end_date": "2024-05-12",
  "weights": {
    "atr": 0.25,
    "mom": 0.25,
    "vol": 0.15,
    "liq": 0.2,
    "dist": 0.15
  },
  "filters": {
    "min_price": 50.0,
    "min_adv_lakh": 100.0
  },
  "top_n": 10,
  "stocks": [
    {
      "symbol": "TARIL",
      "close": 294.15,
      "atr_pct": 7.056603773584907,
      "ret_60d_pct": 85.3146853146853,
      "vol_spike": 1.3025637706801203,
      "adv_lakh": 2977.7272617800004,
      "dist_52w_high_pct": -23.507996359381103,
      "dist_52w_low_pct": 832.9210275927687,
      "bars": 269,
      "name": "Transformers And Rectifiers (India) Ltd.",
      "score_atr": 1.0,
      "score_mom": 0.6229739690494409,
      "score_vol": 0.33964029910603666,
      "score_liq": 0.010741723543353317,
      "score_dist": 0.35894979034846375,
      "composite": 0.5126803503892059,
      "rank": 1
    },
    {
      "symbol": "FORCEMOT",
      "close": 9086.05,
      "atr_pct": 5.8299811249112645,
      "ret_60d_pct": 157.48636202621324,
      "vol_spike": 0.553360848457507,
      "adv_lakh": 9252.192866700001,
      "dist_52w_high_pct": -11.595810407818766,
      "dist_52w_low_pct": 632.0965272741921,
      "bars": 194,
      "name": "Force Motors Ltd.",
      "score_atr": 0.7691987652881254,
      "score_mom": 1.0,
      "score_vol": 0.10393585444235623,
      "score_liq": 0.036018824431139934,
      "score_dist": 0.1747979530248836,
      "composite": 0.4913135273283453,
      "rank": 2
    },
    {
      "symbol": "AEGISLOG",
      "close": 598.6,
      "atr_pct": 6.630888740394253,
      "ret_60d_pct": 63.753248529612904,
      "vol_spike": 0.29383376582702747,
      "adv_lakh": 18707.514290649997,
      "dist_52w_high_pct": -15.38624637783589,
      "dist_52w_low_pct": 113.78571428571429,
      "bars": 270,
      "name": "Aegis Logistics Ltd.",
      "score_atr": 0.919897488113354,
      "score_mom": 0.5103366672286734,
      "score_vol": 0.02228683109748184,
      "score_liq": 0.0741102139786776,
      "score_dist": 0.2333947337479458,
      "composite": 0.41073281635805653,
      "rank": 3
    },
    {
      "symbol": "COCHINSHIP",
      "close": 1229.75,
      "atr_pct": 5.942671274649318,
      "ret_60d_pct": 52.68810528929724,
      "vol_spike": 0.6157413905181001,
      "adv_lakh": 57000.785547425,
      "dist_52w_high_pct": -10.75834542815675,
      "dist_52w_low_pct": 424.4583759808939,
      "bars": 270,
      "name": "Cochin Shipyard Ltd.",
      "score_atr": 0.7904025362502323,
      "score_mom": 0.45253217621663,
      "score_vol": 0.1235612063838461,
      "score_liq": 0.22837719730900102,
      "score_dist": 0.16185148666463606,
      "composite": 0.3992210215357881,
      "rank": 4
    },
    {
      "symbol": "POWERINDIA",
      "close": 8761.4,
      "atr_pct": 6.349727212545943,
      "ret_60d_pct": 45.81918647227214,
      "vol_spike": 0.8549038194276083,
      "adv_lakh": 13144.74522925,
      "dist_52w_high_pct": -12.296981436157708,
      "dist_52w_low_pct": 138.411929576315,
      "bars": 270,
      "name": "Hitachi Energy India Ltd.",
      "score_atr": 0.8669941540268394,
      "score_mom": 0.41664883088635696,
      "score_vol": 0.19880336817800776,
      "score_liq": 0.05170022982477473,
      "score_dist": 0.18563743569176938,
      "composite": 0.3889169127737206,
      "rank": 5
    },
    {
      "symbol": "HINDZINC",
      "close": 525.5,
      "atr_pct": 5.160799238820171,
      "ret_60d_pct": 70.45085955238403,
      "vol_spike": 1.5129084363049141,
      "adv_lakh": 29799.378502174997,
      "dist_52w_high_pct": -2.8560865144653005,
      "dist_52w_low_pct": 84.64511595221363,
      "bars": 270,
      "name": "Hindustan Zinc Ltd.",
      "score_atr": 0.6432855468067518,
      "score_mom": 0.5453250978128664,
      "score_vol": 0.40581619234998734,
      "score_liq": 0.1187945247012514,
      "score_dist": 0.0396895674434153,
      "composite": 0.3877374300641653,
      "rank": 6
    },
    {
      "symbol": "PAYTM",
      "close": 349.65,
      "atr_pct": 3.956813956813955,
      "ret_60d_pct": -17.18379914732354,
      "vol_spike": 2.4115695121253635,
      "adv_lakh": 9466.74081675,
      "dist_52w_high_pct": -64.97545827907443,
      "dist_52w_low_pct": 12.790322580645153,
      "bars": 270,
      "name": "One 97 Communications Ltd.",
      "score_atr": 0.41674375747778863,
      "score_mom": 0.08752019360755674,
      "score_vol": 0.6885412105449729,
      "score_liq": 0.03688314507932855,
      "score_dist": 1.0,
      "composite": 0.386723798368948,
      "rank": 7
    },
    {
      "symbol": "SONATSOFTW",
      "close": 517.8,
      "atr_pct": 5.3254152182309795,
      "ret_60d_pct": -33.93722888491963,
      "vol_spike": 2.708665739676393,
      "adv_lakh": 7330.3253156499995,
      "dist_52w_high_pct": -40.482758620689665,
      "dist_52w_low_pct": 28.97280063764071,
      "bars": 270,
      "name": "Sonata Software Ltd.",
      "score_atr": 0.6742596783723168,
      "score_mom": 0.0,
      "score_vol": 0.7820097479057795,
      "score_liq": 0.028276453520259204,
      "score_dist": 0.6213645705795399,
      "composite": 0.38472635806992894,
      "rank": 8
    },
    {
      "symbol": "CARTRADE",
      "close": 935.6,
      "atr_pct": 4.481348867037195,
      "ret_60d_pct": 35.53527451832539,
      "vol_spike": 3.3516849603463292,
      "adv_lakh": 6872.530301074999,
      "dist_52w_high_pct": -3.9030402629416594,
      "dist_52w_low_pct": 129.8771498771499,
      "bars": 270,
      "name": "Cartrade Tech Ltd.",
      "score_atr": 0.515440210751265,
      "score_mom": 0.36292550501519516,
      "score_vol": 0.9843080623149771,
      "score_liq": 0.026432195937547413,
      "score_dist": 0.05587454450461074,
      "composite": 0.3809052591520627,
      "rank": 9
    },
    {
      "symbol": "MRPL",
      "close": 210.55,
      "atr_pct": 6.186179054856326,
      "ret_60d_pct": 13.841578805082477,
      "vol_spike": 0.8838126968473219,
      "adv_lakh": 18847.479920625,
      "dist_52w_high_pct": -27.208297320656865,
      "dist_52w_low_pct": 246.5843621399177,
      "bars": 270,
      "name": "Mangalore Refinery & Petrochemicals Ltd.",
      "score_atr": 0.8362209437241989,
      "score_mom": 0.2495972803696024,
      "score_vol": 0.2078983018681347,
      "score_liq": 0.07467407480324353,
      "score_dist": 0.41615316372090266,
      "composite": 0.3799970908224546,
      "rank": 10
    }
  ]
}