{
  "model": "n20_daily_large_only",
  "start": "2021-03-01",
  "end": "2026-05-31",
  "years": 5.248,
  "capital": 1000000.0,
  "final_nav": 3711081.0,
  "total_return_pct": 271.11,
  "cagr_pct": 28.38,
  "max_dd_pct": 43.92,
  "max_dd_realized_pct": 37.91,
  "calmar": 0.65,
  "trades": 138,
  "wins": 80,
  "losses": 58,
  "win_rate_pct": 58.0,
  "open_position": {
    "sym": "ADANIENT",
    "qty": 1263,
    "entry_px": 2846.0
  },
  "per_year": {
    "2021": {
      "ret_pct": -4.0,
      "dd_pct": 27.5
    },
    "2022": {
      "ret_pct": 22.1,
      "dd_pct": 35.4
    },
    "2023": {
      "ret_pct": 9.0,
      "dd_pct": 21.4
    },
    "2024": {
      "ret_pct": 55.6,
      "dd_pct": 22.5
    },
    "2025": {
      "ret_pct": 37.8,
      "dd_pct": 21.9
    },
    "2026": {
      "ret_pct": 33.3,
      "dd_pct": 30.9
    }
  },
  "charges_total": 468280.8,
  "fill_at_next_open": true,
  "charges_model": "fyers_cnc"
}